lite_code/__init__.py
lite_code/__main__.py
lite_code/agent.py
lite_code/ask_agent.py
lite_code/cli.py
lite_code/commands.py
lite_code/completer.py
lite_code/config.py
lite_code/tools.py
lite_code/utils.py
lite_code-0.3.2.dist-info/licenses/LICENSE
lite_code-0.3.2.dist-info/METADATA
lite_code-0.3.2.dist-info/WHEEL
lite_code-0.3.2.dist-info/entry_points.txt
lite_code-0.3.2.dist-info/top_level.txt
lite_code-0.3.2.dist-info/RECORD
