Metadata-Version: 2.4
Name: lite-code
Version: 0.3.2
Summary: AI-powered code assistant with interactive CLI
Author-email: Sahil Kumar <sahilkgandash@gmail.com>
Maintainer-email: Sahil Kumar <sahilkgandash@gmail.com>
License: MIT
Project-URL: Homepage, https://github.com/kumarsahil01/lite-code
Project-URL: Documentation, https://github.com/kumarsahil01/lite-code#readme
Project-URL: Repository, https://github.com/kumarsahil01/lite-code.git
Project-URL: Issues, https://github.com/kumarsahil01/lite-code/issues
Keywords: code-refactoring,ai,cli,cerebras,llm,python,javascript,typescript
Classifier: Development Status :: 4 - Beta
Classifier: Intended Audience :: Developers
Classifier: License :: OSI Approved :: MIT License
Classifier: Programming Language :: Python :: 3
Classifier: Programming Language :: Python :: 3.10
Classifier: Programming Language :: Python :: 3.11
Classifier: Programming Language :: Python :: 3.12
Classifier: Topic :: Software Development :: Code Generators
Classifier: Topic :: Software Development :: Libraries :: Python Modules
Requires-Python: >=3.10
License-File: LICENSE
Requires-Dist: cerebras-cloud-sdk>=0.1.0
Requires-Dist: rich>=13.0.0
Requires-Dist: prompt-toolkit>=3.0.0
Provides-Extra: dev
Requires-Dist: pytest>=7.0.0; extra == "dev"
Requires-Dist: black>=23.0.0; extra == "dev"
Requires-Dist: mypy>=1.0.0; extra == "dev"
Dynamic: license-file
